smartTable/__init__.py
smartTable/codeTable.py
smartTable/smartTable.py
smartTable-1.0.1.dist-info/LICENSE
smartTable-1.0.1.dist-info/METADATA
smartTable-1.0.1.dist-info/WHEEL
smartTable-1.0.1.dist-info/top_level.txt
smartTable-1.0.1.dist-info/RECORD
