Metadata-Version: 2.1
Name: smartTable
Version: 1.0.1
Summary: Module Python pour la manipulation et la visualisation de tableaux dynamiques
Home-page: https://github.com/NassAbd/smartTable
Author: Abdallah Nassur
Author-email: nassur1607@gmail.com
License: MIT
Classifier: Programming Language :: Python :: 3
Classifier: License :: OSI Approved :: MIT License
Classifier: Operating System :: OS Independent
Requires-Python: >=3.7
License-File: LICENSE
Requires-Dist: numpy >=1.21
Requires-Dist: pandas >=1.3
Requires-Dist: matplotlib >=3.0
